DeepSeek-OCR-vllm/config.py
DeepSeek-OCR-vllm/deepseek_ocr.py
DeepSeek-OCR-vllm/run_dpsk_ocr_pdf.py
DeepSeek-OCR-vllm/test_14_final.py
DeepSeek-OCR-vllm/deepencoder/__init__.py
DeepSeek-OCR-vllm/deepencoder/build_linear.py
DeepSeek-OCR-vllm/deepencoder/clip_sdpa.py
DeepSeek-OCR-vllm/deepencoder/sam_vary_sdpa.py
DeepSeek-OCR-vllm/process/__init__.py
DeepSeek-OCR-vllm/process/image_process.py
DeepSeek-OCR-vllm/process/ngram_norepeat.py
mcp_server_pdf_to_markdown/__init__.py
mcp_server_pdf_to_markdown/__main__.py
mcp_server_pdf_to_markdown/server.py
mcp_server_pdf_to_markdown-0.2.0.dist-info/METADATA
mcp_server_pdf_to_markdown-0.2.0.dist-info/WHEEL
mcp_server_pdf_to_markdown-0.2.0.dist-info/entry_points.txt
mcp_server_pdf_to_markdown-0.2.0.dist-info/top_level.txt
mcp_server_pdf_to_markdown-0.2.0.dist-info/RECORD
