Metadata-Version: 2.4
Name: mcp-server-pdf-to-markdown
Version: 0.2.0
Summary: 使用 DeepSeek-OCR 将 PDF 转换为 Markdown 的 MCP 工具
Requires-Python: >=3.10
Requires-Dist: addict>=2.4.0
Requires-Dist: easydict>=1.13
Requires-Dist: einops>=0.8.1
Requires-Dist: img2pdf>=0.6.3
Requires-Dist: mcp>=1.23.1
Requires-Dist: numpy>=2.2.6
Requires-Dist: openai>=2.8.1
Requires-Dist: openai-agents>=0.6.1
Requires-Dist: pillow>=12.0.0
Requires-Dist: pydantic>=2.12.5
Requires-Dist: pymupdf>=1.26.6
Requires-Dist: python-dotenv>=1.2.1
Requires-Dist: torch==2.6.0
Requires-Dist: torchaudio==2.6.0
Requires-Dist: torchvision==0.21.0
Requires-Dist: vllm==0.8.5
Requires-Dist: tqdm>=4.66.0
Requires-Dist: transformers>=4.40.0
